customexcelread/__init__.py
customexcelread/main.py
customexcelread_1/__init__.py
customexcelread_1/main.py
customexcelread_1-0.0.1.dist-info/Licence.txt
customexcelread_1-0.0.1.dist-info/METADATA
customexcelread_1-0.0.1.dist-info/WHEEL
customexcelread_1-0.0.1.dist-info/top_level.txt
customexcelread_1-0.0.1.dist-info/RECORD
