Metadata-Version: 2.1
Name: customexcelread-1
Version: 0.0.1
Summary: A brief description of my library
Author: Aravind
Author-email: aravind@gmail.com
Classifier: Development Status :: 3 - Alpha
Classifier: Intended Audience :: Developers
Classifier: License :: OSI Approved :: MIT License
Classifier: Programming Language :: Python :: 3.8
Classifier: Programming Language :: Python :: 3.9
Classifier: Programming Language :: Python :: 3.10
Classifier: Programming Language :: Python :: 3.11
License-File: Licence.txt
